odoo9_addon_account_move_bankaccount_import-9.0.1.0.0.99.dev74-py2.7-nspkg.pth
odoo9_addon_account_move_bankaccount_import-9.0.1.0.0.99.dev74.dist-info/METADATA
odoo9_addon_account_move_bankaccount_import-9.0.1.0.0.99.dev74.dist-info/RECORD
odoo9_addon_account_move_bankaccount_import-9.0.1.0.0.99.dev74.dist-info/WHEEL
odoo9_addon_account_move_bankaccount_import-9.0.1.0.0.99.dev74.dist-info/namespace_packages.txt
odoo9_addon_account_move_bankaccount_import-9.0.1.0.0.99.dev74.dist-info/top_level.txt
odoo_addons/account_move_bankaccount_import/README.rst
odoo_addons/account_move_bankaccount_import/__init__.py
odoo_addons/account_move_bankaccount_import/__openerp__.py
odoo_addons/account_move_bankaccount_import/data/completion_rule_data.xml
odoo_addons/account_move_bankaccount_import/i18n/account_move_bankaccount_import.pot
odoo_addons/account_move_bankaccount_import/i18n/ca.po
odoo_addons/account_move_bankaccount_import/i18n/de.po
odoo_addons/account_move_bankaccount_import/i18n/es.po
odoo_addons/account_move_bankaccount_import/i18n/fi.po
odoo_addons/account_move_bankaccount_import/i18n/fr.po
odoo_addons/account_move_bankaccount_import/i18n/hr_HR.po
odoo_addons/account_move_bankaccount_import/i18n/pt_BR.po
odoo_addons/account_move_bankaccount_import/models/__init__.py
odoo_addons/account_move_bankaccount_import/models/account_move.py
odoo_addons/account_move_bankaccount_import/models/res_partner_bank.py
odoo_addons/account_move_bankaccount_import/static/description/icon.png
odoo_addons/account_move_bankaccount_import/tests/__init__.py
odoo_addons/account_move_bankaccount_import/tests/test_bankaccount_completion.py
